number_game/__init__.py
number_game/__main__.py
advanced_number_game-1.0.0.dist-info/METADATA
advanced_number_game-1.0.0.dist-info/WHEEL
advanced_number_game-1.0.0.dist-info/entry_points.txt
advanced_number_game-1.0.0.dist-info/top_level.txt
advanced_number_game-1.0.0.dist-info/RECORD
